enterprise/LICENSE.md
enterprise/README.md
enterprise/__init__.py
enterprise/cloudformation_stack/litellm.yaml
enterprise/enterprise_callbacks/example_logging_api.py
enterprise/enterprise_callbacks/generic_api_callback.py
enterprise/enterprise_hooks/aporia_ai.py
enterprise/enterprise_hooks/banned_keywords.py
enterprise/enterprise_hooks/blocked_user_list.py
enterprise/enterprise_hooks/google_text_moderation.py
enterprise/enterprise_hooks/llama_guard.py
enterprise/enterprise_hooks/llm_guard.py
enterprise/enterprise_hooks/openai_moderation.py
enterprise/enterprise_hooks/secret_detection.py
enterprise/enterprise_hooks/secrets_plugins/__init__.py
enterprise/enterprise_hooks/secrets_plugins/adafruit.py
enterprise/enterprise_hooks/secrets_plugins/adobe.py
enterprise/enterprise_hooks/secrets_plugins/age_secret_key.py
enterprise/enterprise_hooks/secrets_plugins/airtable_api_key.py
enterprise/enterprise_hooks/secrets_plugins/algolia_api_key.py
enterprise/enterprise_hooks/secrets_plugins/alibaba.py
enterprise/enterprise_hooks/secrets_plugins/asana.py
enterprise/enterprise_hooks/secrets_plugins/atlassian_api_token.py
enterprise/enterprise_hooks/secrets_plugins/authress_access_key.py
enterprise/enterprise_hooks/secrets_plugins/beamer_api_token.py
enterprise/enterprise_hooks/secrets_plugins/bitbucket.py
enterprise/enterprise_hooks/secrets_plugins/bittrex.py
enterprise/enterprise_hooks/secrets_plugins/clojars_api_token.py
enterprise/enterprise_hooks/secrets_plugins/codecov_access_token.py
enterprise/enterprise_hooks/secrets_plugins/coinbase_access_token.py
enterprise/enterprise_hooks/secrets_plugins/confluent.py
enterprise/enterprise_hooks/secrets_plugins/contentful_api_token.py
enterprise/enterprise_hooks/secrets_plugins/databricks_api_token.py
enterprise/enterprise_hooks/secrets_plugins/datadog_access_token.py
enterprise/enterprise_hooks/secrets_plugins/defined_networking_api_token.py
enterprise/enterprise_hooks/secrets_plugins/digitalocean.py
litellm_plus-1.65.1b1.dist-info/LICENSE
litellm_plus-1.65.1b1.dist-info/METADATA
litellm_plus-1.65.1b1.dist-info/WHEEL
litellm_plus-1.65.1b1.dist-info/entry_points.txt
litellm_plus-1.65.1b1.dist-info/RECORD
