Metadata-Version: 2.3
Name: litellm-plus
Version: 1.65.1b1
Summary: Library to easily interface with LLM API providers
License: MIT
Author: BerriAI
Requires-Python: >=3.8, !=2.7.*, !=3.0.*, !=3.1.*, !=3.2.*, !=3.3.*, !=3.4.*, !=3.5.*, !=3.6.*, !=3.7.*
Classifier: License :: OSI Approved :: MIT License
Classifier: Programming Language :: Python :: 3
Classifier: Programming Language :: Python :: 3.9
Classifier: Programming Language :: Python :: 3.10
Classifier: Programming Language :: Python :: 3.11
Classifier: Programming Language :: Python :: 3.12
Classifier: Programming Language :: Python :: 3.13
Provides-Extra: extra-proxy
Provides-Extra: proxy
Requires-Dist: PyJWT (>=2.8.0,<3.0.0) ; extra == "proxy"
Requires-Dist: aiohttp
Requires-Dist: apscheduler (>=3.10.4,<4.0.0) ; extra == "proxy"
Requires-Dist: azure-identity (>=1.15.0,<2.0.0) ; extra == "extra-proxy"
Requires-Dist: azure-keyvault-secrets (>=4.8.0,<5.0.0) ; extra == "extra-proxy"
Requires-Dist: backoff ; extra == "proxy"
Requires-Dist: boto3 (==1.34.34) ; extra == "proxy"
Requires-Dist: click
Requires-Dist: cryptography (>=43.0.1,<44.0.0) ; extra == "proxy"
Requires-Dist: fastapi (>=0.115.5,<0.116.0) ; extra == "proxy"
Requires-Dist: fastapi-sso (>=0.16.0,<0.17.0) ; extra == "proxy"
Requires-Dist: google-cloud-kms (>=2.21.3,<3.0.0) ; extra == "extra-proxy"
Requires-Dist: gunicorn (>=23.0.0,<24.0.0) ; extra == "proxy"
Requires-Dist: httpx (>=0.23.0)
Requires-Dist: importlib-metadata (>=6.8.0)
Requires-Dist: jinja2 (>=3.1.2,<4.0.0)
Requires-Dist: jsonschema (>=4.22.0,<5.0.0)
Requires-Dist: litellm-proxy-extras (==0.1.1) ; extra == "proxy"
Requires-Dist: mcp (==1.5.0) ; (python_version >= "3.10") and (extra == "proxy")
Requires-Dist: openai (>=1.68.2)
Requires-Dist: orjson (>=3.9.7,<4.0.0) ; extra == "proxy"
Requires-Dist: prisma (==0.11.0) ; extra == "extra-proxy"
Requires-Dist: pydantic (>=2.0.0,<3.0.0)
Requires-Dist: pynacl (>=1.5.0,<2.0.0) ; extra == "proxy"
Requires-Dist: python-dotenv (>=0.2.0)
Requires-Dist: python-multipart (>=0.0.18,<0.0.19) ; extra == "proxy"
Requires-Dist: pyyaml (>=6.0.1,<7.0.0) ; extra == "proxy"
Requires-Dist: redisvl (>=0.4.1,<0.5.0) ; (python_version >= "3.9" and python_version < "3.14") and (extra == "extra-proxy")
Requires-Dist: resend (>=0.8.0,<0.9.0) ; extra == "extra-proxy"
Requires-Dist: rq ; extra == "proxy"
Requires-Dist: tiktoken (>=0.7.0)
Requires-Dist: tokenizers
Requires-Dist: uvicorn (>=0.29.0,<0.30.0) ; extra == "proxy"
Requires-Dist: uvloop (>=0.21.0,<0.22.0) ; extra == "proxy"
Requires-Dist: websockets (>=13.1.0,<14.0.0) ; extra == "proxy"
Project-URL: Documentation, https://docs.litellm.ai
Project-URL: Homepage, https://litellm.ai
Project-URL: Repository, https://github.com/BerriAI/litellm
Project-URL: documentation, https://docs.litellm.ai
Project-URL: homepage, https://litellm.ai
Project-URL: repository, https://github.com/BerriAI/litellm
